{"description":"Desert Map created from image.","map_id":"82","objects":[{"position":"(-664, -728)","type":"rock"},{"position":"(-504, -888)","type":"rock"},{"position":"(-232, 168)","type":"rock"},{"position":"(904, 8)","type":"rock"},{"position":"(-472, -1016)","type":"rock"},{"position":"(840, -56)","type":"rock"},{"position":"(-1096, -1000)","type":"rock"},{"position":"(712, 808)","type":"rock"},{"position":"(-1048, 264)","type":"rock"},{"position":"(56, 1112)","type":"rock"},{"position":"(-184, -1128)","type":"rock"},{"position":"(-1016, -424)","type":"rock"},{"position":"(1144, 792)","type":"rock"},{"position":"(-856, 1000)","type":"rock"},{"position":"(1016, -72)","type":"rock"},{"position":"(840, -1160)","type":"rock"},{"position":"(-1048, 296)","type":"rock"},{"position":"(-264, -600)","type":"rock"},{"position":"(-728, -88)","type":"rock"},{"position":"(296, -184)","type":"rock"}],"privacy":1}